savefigs/__init__.py
savefigs/py.typed
savefigs-0.2.1.dist-info/LICENSE
savefigs-0.2.1.dist-info/WHEEL
savefigs-0.2.1.dist-info/METADATA
savefigs-0.2.1.dist-info/RECORD
