Metadata-Version: 2.1
Name: savefigs
Version: 0.2.1
Summary: Save all open Matplotlib figures
Author-email: zmoon <zmoon92@gmail.com>
Requires-Python: ~=3.7
Requires-Dist: matplotlib ~=3.0
Requires-Dist: ipython ; extra == "dev"
Requires-Dist: pdoc ; extra == "dev"
Requires-Dist: mypy ; extra == "test"
Requires-Dist: pytest ; extra == "test"
Project-URL: Documentation, https://github.com/zmoon/savefigs
Project-URL: Home, https://github.com/zmoon/savefigs
Project-URL: Source, https://github.com/zmoon/savefigs
Provides-Extra: dev
Provides-Extra: test
